turning_function.cp39-win_amd64.pyd
turning_function-0.0.3.dist-info/METADATA
turning_function-0.0.3.dist-info/WHEEL
turning_function-0.0.3.dist-info/top_level.txt
turning_function-0.0.3.dist-info/RECORD
