Metadata-Version: 2.1
Name: turning-function
Version: 0.0.3
Summary: Python implementation of "An efficiently computable metric for comparing polygonal shapes" (Arkin et al.)
Home-page: https://github.com/DBraun/turning-function
Author: David Braun
Author-email: braun@ccrma.stanford.edu
Requires-Python: >=3.6
Provides-Extra: test
Requires-Dist: pytest ; extra == 'test'
